setup.py
t_io/__init__.py
t_io.egg-info/PKG-INFO
t_io.egg-info/SOURCES.txt
t_io.egg-info/dependency_links.txt
t_io.egg-info/top_level.txt
t_io.egg-info/zip-safe