Metadata-Version: 1.0
Name: t-io
Version: 0.1
Summary: T IO library
Home-page: https://gitlab.com/ddmello/lib/python/threads_io.git
Author: Darrin D'Mello
Author-email: darrin.dmello@gmail.com
License: MIT
Platform: UNKNOWN
